chango/__about__.py
chango/__init__.py
chango/__main__.py
chango/_changenoteinfo.py
chango/_version.py
chango/action.py
chango/constants.py
chango/error.py
chango/helpers.py
chango/py.typed
chango/_cli/__init__.py
chango/_cli/config.py
chango/_cli/edit.py
chango/_cli/new.py
chango/_cli/release.py
chango/_cli/report.py
chango/_cli/utils/__init__.py
chango/_cli/utils/types.py
chango/_utils/__init__.py
chango/_utils/config.py
chango/_utils/filename.py
chango/_utils/files.py
chango/_utils/strings.py
chango/_utils/types.py
chango/abc/__init__.py
chango/abc/_changenote.py
chango/abc/_chango.py
chango/abc/_versionhistory.py
chango/abc/_versionnote.py
chango/abc/_versionscanner.py
chango/concrete/__init__.py
chango/concrete/_backwardcompatiblechango.py
chango/concrete/_backwardcompatibleversionscanner.py
chango/concrete/_commentchangenote.py
chango/concrete/_commentversionnote.py
chango/concrete/_directorychango.py
chango/concrete/_directoryversionscanner.py
chango/concrete/_headerversionhistory.py
chango/concrete/sections/__init__.py
chango/concrete/sections/_githubsectionchangenote.py
chango/concrete/sections/_pullrequest.py
chango/concrete/sections/_section.py
chango/concrete/sections/_sectionchangenote.py
chango/concrete/sections/_sectionversionnote.py
chango/config/__init__.py
chango/config/_models.py
chango/sphinx_ext/__init__.py
chango/sphinx_ext/_util.py
chango-0.6.1.dist-info/METADATA
chango-0.6.1.dist-info/WHEEL
chango-0.6.1.dist-info/entry_points.txt
chango-0.6.1.dist-info/licenses/LICENSE.txt
chango-0.6.1.dist-info/RECORD
