Metadata-Version: 2.4
Name: chango
Version: 0.6.1
Summary: CHANgelog GOvernor for Your Project
Project-URL: Documentation, https://chango.readthedocs.io/
Project-URL: Issues, https://github.com/Bibo-Joshi/chango/issues
Project-URL: Source, https://github.com/Bibo-Joshi/chango
Author-email: Hinrich Mahler <chango@mahlerhome.de>
License-Expression: MIT
License-File: LICENSE.txt
Keywords: changelog,development,releasenotes,versioning
Classifier: Development Status :: 4 - Beta
Classifier: Framework :: Sphinx :: Extension
Classifier: Intended Audience :: Developers
Classifier: License :: OSI Approved :: MIT License
Classifier: Operating System :: OS Independent
Classifier: Programming Language :: Python
Classifier: Programming Language :: Python :: 3.12
Classifier: Programming Language :: Python :: 3.13
Classifier: Topic :: Software Development :: Documentation
Classifier: Topic :: Software Development :: Libraries :: Python Modules
Requires-Python: >=3.12
Requires-Dist: pydantic-settings~=2.3
Requires-Dist: shortuuid~=1.0
Requires-Dist: sphinx<10.0,>=8.1
Requires-Dist: tomlkit~=0.13
Requires-Dist: typer~=0.12
